{
  "subject_dependent": {
    "A01": {
      "train": [
        242,
        41,
        136,
        69,
        137,
        47,
        283,
        264,
        102,
        183,
        93,
        138,
        200,
        165,
        38,
        82,
        29,
        15,
        210,
        180,
        157,
        59,
        254,
        173,
        159,
        64,
        3,
        150,
        97,
        30,
        88,
        72,
        140,
        222,
        199,
        212,
        278,
        101,
        262,
        55,
        94,
        65,
        178,
        251,
        10,
        134,
        177,
        147,
        67,
        256,
        189,
        11,
        217,
        196,
        35,
        17,
        76,
        281,
        37,
        78,
        48,
        45,
        2,
        258,
        176,
        241,
        103,
        62,
        143,
        124,
        53,
        119,
        141,
        219,
        142,
        205,
        0,
        57,
        214,
        167,
        90,
        92,
        54,
        270,
        66,
        110,
        271,
        285,
        1,
        245,
        228,
        56,
        195,
        266,
        75,
        128,
        100,
        121,
        265,
        286,
        163,
        105,
        130,
        218,
        249,
        230,
        9,
        68,
        39,
        153,
        113,
        60,
        208,
        170,
        221,
        115,
        96,
        247,
        209,
        98,
        160,
        268,
        225,
        155,
        273,
        166,
        107,
        80,
        19,
        133,
        127,
        139,
        116,
        261,
        129,
        109,
        120,
        71,
        184,
        234,
        193,
        112,
        149,
        77,
        12,
        201,
        179,
        117,
        22,
        122,
        46,
        239,
        79,
        190,
        43,
        185,
        111,
        44,
        26,
        20,
        287,
        274,
        207,
        148,
        158,
        188,
        33,
        114,
        95,
        154,
        50,
        81,
        248,
        280,
        220,
        203,
        275,
        86,
        152,
        243,
        191,
        272,
        197,
        238,
        168,
        276,
        279,
        18,
        91,
        164,
        151,
        224,
        236,
        226,
        25,
        231,
        171,
        215,
        237,
        244,
        4
      ],
      "val": [
        267,
        182,
        235,
        192,
        8,
        13,
        5,
        161,
        31,
        282,
        156,
        233,
        63,
        206,
        108,
        284,
        144,
        198,
        49,
        42,
        253,
        257,
        126,
        211,
        40,
        229,
        83,
        14,
        85,
        36,
        87,
        172,
        125,
        6,
        246,
        24,
        70,
        123,
        131,
        23,
        146,
        52,
        106
      ],
      "test": [
        174,
        162,
        51,
        260,
        99,
        61,
        223,
        7,
        186,
        27,
        74,
        232,
        21,
        213,
        263,
        250,
        118,
        169,
        259,
        181,
        104,
        84,
        135,
        269,
        28,
        73,
        202,
        32,
        175,
        252,
        216,
        204,
        240,
        132,
        227,
        194,
        34,
        89,
        187,
        145,
        16,
        58,
        277,
        255
      ],
      "session": "T"
    },
    "A02": {
      "train": [
        247,
        131,
        218,
        51,
        185,
        46,
        219,
        35,
        177,
        12,
        102,
        161,
        269,
        188,
        107,
        142,
        54,
        134,
        20,
        28,
        277,
        260,
        61,
        193,
        7,
        36,
        135,
        156,
        33,
        113,
        43,
        214,
        2,
        194,
        165,
        30,
        191,
        69,
        248,
        73,
        268,
        204,
        9,
        95,
        221,
        236,
        286,
        186,
        52,
        262,
        44,
        176,
        88,
        65,
        252,
        238,
        270,
        45,
        94,
        38,
        93,
        77,
        234,
        211,
        47,
        287,
        244,
        225,
        87,
        207,
        137,
        274,
        202,
        181,
        23,
        48,
        5,
        212,
        39,
        3,
        190,
        200,
        154,
        85,
        83,
        157,
        136,
        175,
        110,
        271,
        58,
        122,
        192,
        180,
        215,
        19,
        174,
        32,
        279,
        105,
        79,
        256,
        184,
        13,
        250,
        168,
        103,
        124,
        24,
        179,
        253,
        150,
        125,
        111,
        249,
        64,
        278,
        114,
        17,
        169,
        82,
        60,
        254,
        217,
        148,
        139,
        37,
        68,
        6,
        171,
        231,
        163,
        232,
        282,
        106,
        81,
        223,
        27,
        216,
        251,
        108,
        228,
        240,
        115,
        145,
        230,
        70,
        226,
        26,
        267,
        187,
        183,
        159,
        127,
        160,
        237,
        272,
        235,
        80,
        138,
        89,
        162,
        112,
        129,
        55,
        273,
        155,
        41,
        229,
        15,
        71,
        149,
        0,
        246,
        255,
        126,
        90,
        133,
        167,
        76,
        146,
        75,
        147,
        99,
        206,
        210,
        158,
        118,
        170,
        153,
        97,
        152,
        261,
        196,
        91,
        222,
        224,
        11,
        4,
        16,
        197
      ],
      "val": [
        178,
        141,
        22,
        166,
        31,
        121,
        98,
        78,
        132,
        208,
        42,
        263,
        128,
        243,
        25,
        101,
        62,
        266,
        74,
        40,
        275,
        264,
        104,
        220,
        143,
        281,
        209,
        117,
        284,
        205,
        258,
        182,
        21,
        172,
        53,
        119,
        198,
        259,
        123,
        10,
        34,
        164,
        233
      ],
      "test": [
        8,
        49,
        56,
        201,
        66,
        285,
        203,
        130,
        140,
        63,
        1,
        29,
        92,
        18,
        50,
        116,
        144,
        242,
        86,
        265,
        189,
        72,
        283,
        213,
        280,
        14,
        257,
        57,
        100,
        245,
        109,
        227,
        67,
        199,
        195,
        151,
        120,
        239,
        84,
        96,
        59,
        173,
        241,
        276
      ],
      "session": "T"
    },
    "A03": {
      "train": [
        141,
        193,
        13,
        137,
        209,
        4,
        204,
        228,
        0,
        218,
        179,
        45,
        170,
        150,
        3,
        176,
        33,
        199,
        173,
        83,
        146,
        104,
        76,
        246,
        151,
        30,
        237,
        38,
        91,
        283,
        80,
        47,
        115,
        1,
        221,
        161,
        145,
        190,
        130,
        143,
        101,
        140,
        89,
        172,
        272,
        25,
        8,
        242,
        46,
        220,
        102,
        153,
        96,
        159,
        208,
        157,
        84,
        174,
        234,
        245,
        276,
        44,
        274,
        275,
        10,
        148,
        79,
        67,
        69,
        50,
        191,
        139,
        154,
        194,
        210,
        259,
        287,
        256,
        40,
        247,
        53,
        171,
        128,
        133,
        217,
        225,
        26,
        35,
        200,
        122,
        177,
        73,
        56,
        188,
        72,
        100,
        162,
        125,
        62,
        116,
        166,
        168,
        74,
        113,
        269,
        118,
        243,
        21,
        231,
        64,
        28,
        280,
        227,
        112,
        187,
        99,
        279,
        281,
        132,
        138,
        267,
        61,
        117,
        109,
        164,
        226,
        230,
        262,
        41,
        39,
        12,
        258,
        58,
        29,
        197,
        94,
        31,
        119,
        37,
        241,
        82,
        260,
        34,
        156,
        271,
        219,
        257,
        66,
        16,
        239,
        229,
        270,
        255,
        202,
        266,
        19,
        90,
        192,
        108,
        205,
        43,
        273,
        97,
        235,
        107,
        114,
        180,
        129,
        14,
        85,
        149,
        184,
        135,
        251,
        165,
        51,
        52,
        216,
        277,
        142,
        48,
        134,
        147,
        93,
        182,
        175,
        212,
        71,
        2,
        70,
        167,
        169,
        124,
        223,
        75,
        23,
        282,
        78,
        278,
        7,
        178
      ],
      "val": [
        106,
        214,
        155,
        201,
        284,
        9,
        20,
        183,
        87,
        18,
        206,
        238,
        211,
        265,
        248,
        222,
        195,
        263,
        81,
        5,
        88,
        55,
        127,
        92,
        59,
        236,
        160,
        198,
        121,
        224,
        250,
        105,
        60,
        186,
        254,
        249,
        286,
        27,
        103,
        22,
        98,
        252,
        285
      ],
      "test": [
        233,
        240,
        111,
        152,
        244,
        144,
        54,
        261,
        63,
        253,
        203,
        123,
        77,
        49,
        136,
        232,
        11,
        42,
        6,
        207,
        189,
        185,
        86,
        36,
        158,
        126,
        110,
        196,
        17,
        268,
        24,
        181,
        264,
        215,
        57,
        65,
        15,
        120,
        68,
        163,
        213,
        95,
        32,
        131
      ],
      "session": "T"
    },
    "A04": {
      "train": [
        178,
        121,
        283,
        26,
        12,
        266,
        236,
        268,
        243,
        10,
        136,
        105,
        48,
        86,
        247,
        31,
        211,
        272,
        250,
        155,
        103,
        51,
        65,
        210,
        5,
        17,
        93,
        104,
        71,
        19,
        188,
        96,
        4,
        175,
        110,
        55,
        245,
        43,
        138,
        70,
        265,
        11,
        2,
        85,
        205,
        94,
        222,
        9,
        202,
        233,
        169,
        52,
        91,
        45,
        142,
        186,
        84,
        116,
        8,
        225,
        287,
        275,
        216,
        232,
        22,
        277,
        191,
        36,
        271,
        194,
        264,
        231,
        132,
        81,
        170,
        171,
        129,
        237,
        182,
        167,
        240,
        254,
        280,
        34,
        212,
        173,
        262,
        145,
        152,
        219,
        119,
        163,
        213,
        284,
        246,
        156,
        174,
        115,
        181,
        106,
        122,
        139,
        25,
        62,
        108,
        73,
        196,
        89,
        180,
        263,
        165,
        267,
        199,
        90,
        217,
        13,
        88,
        24,
        190,
        238,
        37,
        33,
        177,
        79,
        77,
        78,
        27,
        42,
        38,
        241,
        74,
        126,
        172,
        21,
        286,
        44,
        273,
        111,
        41,
        234,
        239,
        279,
        184,
        113,
        97,
        75,
        83,
        112,
        228,
        143,
        252,
        60,
        179,
        64,
        0,
        54,
        198,
        18,
        101,
        147,
        49,
        161,
        39,
        123,
        1,
        141,
        162,
        29,
        206,
        15,
        95,
        253,
        229,
        185,
        270,
        260,
        20,
        137,
        149,
        148,
        242,
        135,
        157,
        109,
        251,
        220,
        151,
        166,
        134,
        269,
        67,
        57,
        261,
        87,
        195,
        259,
        218,
        47,
        221,
        207,
        14
      ],
      "val": [
        76,
        68,
        281,
        131,
        187,
        28,
        82,
        227,
        69,
        100,
        276,
        224,
        192,
        153,
        66,
        208,
        255,
        35,
        6,
        230,
        99,
        226,
        159,
        53,
        133,
        118,
        46,
        50,
        164,
        223,
        3,
        249,
        124,
        30,
        201,
        125,
        154,
        7,
        285,
        128,
        256,
        127,
        102
      ],
      "test": [
        214,
        58,
        144,
        140,
        56,
        158,
        183,
        274,
        257,
        160,
        197,
        209,
        61,
        16,
        63,
        117,
        23,
        92,
        80,
        248,
        193,
        204,
        200,
        168,
        244,
        107,
        258,
        176,
        120,
        215,
        150,
        114,
        282,
        59,
        98,
        278,
        32,
        72,
        130,
        235,
        203,
        146,
        40,
        189
      ],
      "session": "T"
    },
    "A05": {
      "train": [
        39,
        230,
        81,
        188,
        32,
        35,
        96,
        248,
        183,
        42,
        152,
        191,
        229,
        271,
        92,
        5,
        261,
        145,
        257,
        82,
        198,
        224,
        130,
        275,
        40,
        217,
        167,
        64,
        243,
        193,
        10,
        148,
        222,
        25,
        251,
        69,
        112,
        13,
        186,
        16,
        15,
        43,
        8,
        226,
        0,
        20,
        60,
        146,
        58,
        3,
        19,
        138,
        63,
        74,
        121,
        47,
        9,
        83,
        274,
        129,
        14,
        22,
        62,
        55,
        164,
        174,
        33,
        143,
        26,
        127,
        201,
        258,
        192,
        182,
        283,
        128,
        107,
        177,
        131,
        197,
        246,
        76,
        165,
        34,
        45,
        168,
        102,
        108,
        260,
        1,
        215,
        36,
        256,
        265,
        204,
        119,
        70,
        94,
        61,
        97,
        67,
        190,
        77,
        221,
        31,
        122,
        189,
        284,
        216,
        158,
        259,
        244,
        38,
        132,
        46,
        78,
        286,
        85,
        273,
        115,
        105,
        166,
        133,
        117,
        210,
        232,
        185,
        249,
        24,
        281,
        18,
        279,
        37,
        282,
        253,
        111,
        231,
        139,
        106,
        99,
        196,
        6,
        287,
        88,
        172,
        126,
        91,
        123,
        180,
        116,
        241,
        212,
        57,
        194,
        277,
        110,
        54,
        44,
        11,
        203,
        49,
        206,
        176,
        278,
        175,
        29,
        252,
        150,
        93,
        104,
        269,
        136,
        7,
        239,
        98,
        250,
        142,
        80,
        118,
        103,
        240,
        30,
        95,
        272,
        41,
        234,
        199,
        17,
        109,
        120,
        155,
        151,
        141,
        245,
        242,
        28,
        157,
        100,
        160,
        56,
        181
      ],
      "val": [
        12,
        140,
        200,
        114,
        262,
        276,
        178,
        149,
        153,
        211,
        134,
        219,
        124,
        154,
        89,
        266,
        207,
        268,
        237,
        247,
        255,
        227,
        280,
        267,
        254,
        187,
        144,
        162,
        2,
        75,
        156,
        52,
        84,
        225,
        51,
        90,
        159,
        236,
        228,
        86,
        213,
        195,
        68
      ],
      "test": [
        205,
        270,
        235,
        184,
        170,
        202,
        171,
        125,
        147,
        21,
        27,
        161,
        79,
        214,
        137,
        101,
        163,
        4,
        209,
        223,
        238,
        66,
        220,
        73,
        48,
        53,
        233,
        169,
        285,
        87,
        65,
        218,
        50,
        113,
        173,
        71,
        263,
        208,
        59,
        23,
        179,
        72,
        264,
        135
      ],
      "session": "T"
    },
    "A06": {
      "train": [
        110,
        271,
        109,
        26,
        179,
        161,
        153,
        244,
        134,
        280,
        198,
        170,
        100,
        223,
        230,
        152,
        62,
        107,
        7,
        213,
        87,
        58,
        167,
        41,
        217,
        159,
        77,
        227,
        283,
        169,
        261,
        201,
        13,
        180,
        42,
        78,
        32,
        95,
        141,
        253,
        94,
        8,
        173,
        81,
        190,
        211,
        120,
        136,
        34,
        40,
        133,
        174,
        82,
        175,
        233,
        241,
        229,
        31,
        191,
        10,
        140,
        147,
        260,
        202,
        146,
        132,
        113,
        119,
        60,
        138,
        199,
        37,
        184,
        53,
        228,
        61,
        76,
        275,
        194,
        165,
        178,
        117,
        71,
        28,
        79,
        197,
        240,
        209,
        281,
        91,
        252,
        139,
        70,
        273,
        126,
        39,
        164,
        24,
        286,
        216,
        69,
        112,
        84,
        254,
        210,
        256,
        155,
        181,
        255,
        97,
        151,
        250,
        93,
        187,
        258,
        243,
        267,
        11,
        249,
        73,
        248,
        195,
        279,
        158,
        111,
        203,
        125,
        68,
        48,
        168,
        276,
        212,
        14,
        27,
        166,
        45,
        215,
        150,
        148,
        25,
        277,
        268,
        272,
        265,
        128,
        20,
        206,
        193,
        116,
        129,
        75,
        19,
        105,
        269,
        5,
        72,
        226,
        172,
        144,
        4,
        36,
        221,
        284,
        224,
        121,
        33,
        232,
        186,
        64,
        17,
        56,
        278,
        123,
        44,
        85,
        135,
        238,
        266,
        98,
        200,
        38,
        205,
        225,
        63,
        163,
        262,
        287,
        80,
        282,
        55,
        86,
        106,
        218,
        88,
        176,
        251,
        29,
        9,
        137,
        171,
        90
      ],
      "val": [
        101,
        263,
        16,
        156,
        145,
        115,
        247,
        222,
        103,
        96,
        99,
        285,
        242,
        35,
        185,
        245,
        46,
        108,
        188,
        114,
        207,
        196,
        183,
        59,
        257,
        122,
        204,
        3,
        182,
        74,
        65,
        2,
        52,
        23,
        1,
        270,
        89,
        124,
        237,
        83,
        57,
        142,
        102
      ],
      "test": [
        43,
        49,
        259,
        160,
        246,
        239,
        15,
        220,
        235,
        131,
        67,
        192,
        50,
        149,
        189,
        130,
        264,
        154,
        12,
        54,
        22,
        47,
        177,
        127,
        162,
        118,
        92,
        21,
        234,
        274,
        18,
        66,
        30,
        143,
        104,
        231,
        219,
        214,
        6,
        157,
        236,
        208,
        51,
        0
      ],
      "session": "T"
    },
    "A07": {
      "train": [
        172,
        24,
        21,
        65,
        26,
        118,
        60,
        100,
        246,
        222,
        195,
        67,
        256,
        178,
        163,
        53,
        241,
        212,
        215,
        78,
        8,
        201,
        279,
        110,
        18,
        267,
        258,
        273,
        282,
        52,
        117,
        105,
        46,
        227,
        238,
        176,
        221,
        73,
        264,
        165,
        198,
        270,
        144,
        168,
        75,
        63,
        70,
        184,
        225,
        4,
        259,
        87,
        171,
        277,
        205,
        216,
        262,
        116,
        214,
        237,
        55,
        189,
        17,
        223,
        164,
        188,
        217,
        281,
        286,
        109,
        69,
        134,
        252,
        284,
        130,
        232,
        19,
        84,
        93,
        272,
        220,
        142,
        38,
        211,
        255,
        250,
        114,
        263,
        218,
        9,
        247,
        149,
        249,
        206,
        104,
        13,
        268,
        231,
        248,
        208,
        89,
        242,
        181,
        253,
        230,
        1,
        199,
        7,
        102,
        285,
        23,
        59,
        45,
        97,
        48,
        42,
        76,
        122,
        179,
        233,
        31,
        257,
        2,
        74,
        213,
        96,
        265,
        27,
        29,
        20,
        236,
        107,
        132,
        32,
        6,
        68,
        145,
        15,
        240,
        115,
        287,
        151,
        11,
        200,
        210,
        174,
        148,
        120,
        72,
        283,
        162,
        157,
        147,
        83,
        193,
        103,
        44,
        0,
        128,
        152,
        123,
        108,
        207,
        94,
        81,
        251,
        51,
        280,
        90,
        129,
        269,
        137,
        16,
        82,
        30,
        234,
        22,
        33,
        150,
        160,
        101,
        275,
        274,
        35,
        127,
        155,
        219,
        88,
        85,
        86,
        10,
        28,
        61,
        261,
        77,
        62,
        278,
        95,
        80,
        111,
        191
      ],
      "val": [
        91,
        245,
        276,
        131,
        229,
        156,
        64,
        57,
        153,
        50,
        34,
        125,
        192,
        119,
        209,
        41,
        121,
        159,
        112,
        186,
        71,
        43,
        25,
        47,
        139,
        136,
        40,
        243,
        169,
        141,
        175,
        254,
        56,
        203,
        99,
        113,
        239,
        170,
        143,
        12,
        154,
        202,
        54
      ],
      "test": [
        106,
        98,
        271,
        133,
        166,
        228,
        14,
        49,
        39,
        158,
        5,
        266,
        58,
        135,
        194,
        3,
        37,
        187,
        183,
        124,
        185,
        66,
        226,
        138,
        180,
        235,
        161,
        167,
        197,
        260,
        204,
        196,
        190,
        79,
        92,
        224,
        140,
        36,
        146,
        177,
        126,
        244,
        182,
        173
      ],
      "session": "T"
    },
    "A08": {
      "train": [
        217,
        166,
        102,
        119,
        269,
        20,
        236,
        74,
        145,
        115,
        81,
        140,
        196,
        127,
        286,
        63,
        235,
        246,
        240,
        66,
        24,
        123,
        287,
        283,
        76,
        85,
        61,
        34,
        182,
        215,
        8,
        39,
        175,
        10,
        25,
        124,
        270,
        193,
        138,
        239,
        31,
        18,
        15,
        268,
        157,
        224,
        173,
        108,
        33,
        16,
        167,
        195,
        161,
        208,
        107,
        181,
        73,
        223,
        209,
        37,
        99,
        88,
        46,
        97,
        120,
        103,
        83,
        1,
        198,
        69,
        114,
        148,
        67,
        260,
        38,
        188,
        23,
        178,
        89,
        96,
        82,
        279,
        172,
        126,
        135,
        149,
        261,
        112,
        257,
        40,
        251,
        202,
        263,
        98,
        72,
        185,
        233,
        216,
        191,
        12,
        151,
        253,
        153,
        200,
        121,
        122,
        247,
        259,
        249,
        219,
        201,
        77,
        276,
        54,
        100,
        242,
        41,
        210,
        177,
        28,
        3,
        144,
        231,
        160,
        48,
        207,
        162,
        243,
        206,
        136,
        194,
        142,
        187,
        262,
        255,
        227,
        232,
        205,
        2,
        118,
        13,
        238,
        55,
        80,
        184,
        220,
        64,
        137,
        57,
        214,
        204,
        244,
        116,
        271,
        117,
        225,
        150,
        90,
        14,
        203,
        113,
        252,
        75,
        168,
        254,
        22,
        277,
        264,
        230,
        282,
        170,
        21,
        131,
        274,
        212,
        169,
        7,
        59,
        179,
        155,
        11,
        245,
        17,
        42,
        111,
        146,
        285,
        68,
        256,
        56,
        125,
        183,
        180,
        5,
        143,
        159,
        248,
        234,
        50,
        27,
        35
      ],
      "val": [
        226,
        213,
        190,
        30,
        104,
        165,
        222,
        280,
        86,
        4,
        78,
        53,
        44,
        241,
        84,
        164,
        65,
        267,
        92,
        197,
        47,
        19,
        32,
        87,
        101,
        171,
        52,
        29,
        9,
        189,
        129,
        211,
        45,
        58,
        266,
        192,
        43,
        186,
        128,
        228,
        36,
        199,
        141
      ],
      "test": [
        62,
        174,
        273,
        152,
        156,
        51,
        275,
        272,
        158,
        139,
        281,
        94,
        221,
        93,
        0,
        110,
        265,
        60,
        26,
        105,
        79,
        130,
        147,
        6,
        106,
        49,
        134,
        218,
        154,
        91,
        163,
        71,
        250,
        95,
        258,
        133,
        237,
        278,
        284,
        229,
        70,
        132,
        109,
        176
      ],
      "session": "T"
    },
    "A09": {
      "train": [
        212,
        19,
        135,
        72,
        271,
        96,
        23,
        282,
        132,
        226,
        170,
        278,
        194,
        199,
        42,
        198,
        64,
        232,
        259,
        85,
        200,
        68,
        142,
        9,
        58,
        204,
        177,
        59,
        244,
        108,
        65,
        209,
        178,
        268,
        262,
        30,
        25,
        171,
        238,
        88,
        149,
        255,
        182,
        39,
        239,
        147,
        207,
        61,
        78,
        104,
        1,
        79,
        89,
        120,
        162,
        206,
        45,
        14,
        240,
        127,
        73,
        18,
        35,
        160,
        27,
        123,
        93,
        0,
        67,
        115,
        223,
        40,
        283,
        208,
        80,
        10,
        153,
        4,
        272,
        247,
        63,
        94,
        269,
        71,
        256,
        180,
        274,
        7,
        251,
        213,
        118,
        217,
        261,
        99,
        51,
        113,
        130,
        161,
        21,
        97,
        126,
        187,
        36,
        284,
        202,
        138,
        134,
        143,
        165,
        176,
        148,
        90,
        193,
        156,
        150,
        8,
        233,
        227,
        44,
        234,
        121,
        145,
        159,
        31,
        286,
        218,
        183,
        215,
        131,
        281,
        220,
        48,
        34,
        56,
        186,
        86,
        50,
        13,
        81,
        254,
        242,
        216,
        43,
        235,
        243,
        210,
        124,
        270,
        230,
        32,
        91,
        11,
        192,
        92,
        201,
        82,
        107,
        114,
        101,
        190,
        15,
        214,
        70,
        173,
        139,
        203,
        166,
        236,
        169,
        29,
        106,
        154,
        258,
        5,
        33,
        275,
        112,
        152,
        263,
        264,
        2,
        280,
        196,
        175,
        111,
        211,
        140,
        83,
        267,
        116,
        46,
        41,
        146,
        181,
        100,
        167,
        265,
        12,
        133,
        231,
        273
      ],
      "val": [
        66,
        237,
        260,
        228,
        285,
        128,
        77,
        188,
        184,
        76,
        172,
        74,
        103,
        157,
        110,
        102,
        225,
        229,
        47,
        53,
        137,
        119,
        174,
        144,
        125,
        246,
        26,
        20,
        84,
        221,
        95,
        179,
        151,
        277,
        62,
        245,
        105,
        257,
        98,
        249,
        155,
        22,
        3
      ],
      "test": [
        49,
        129,
        52,
        241,
        250,
        87,
        69,
        141,
        38,
        185,
        136,
        109,
        117,
        266,
        17,
        55,
        158,
        248,
        189,
        219,
        253,
        252,
        195,
        75,
        191,
        287,
        276,
        205,
        54,
        168,
        24,
        6,
        279,
        163,
        164,
        28,
        60,
        37,
        122,
        222,
        16,
        197,
        224,
        57
      ],
      "session": "T"
    }
  },
  "loso": {
    "fold_0": {
      "train_subjects": [
        "A03",
        "A04",
        "A05",
        "A06",
        "A07",
        "A08",
        "A09"
      ],
      "val_subject": "A02",
      "test_subject": "A01",
      "train_sessions": [
        "T",
        "E"
      ],
      "val_sessions": [
        "T",
        "E"
      ],
      "test_sessions": [
        "T",
        "E"
      ]
    },
    "fold_1": {
      "train_subjects": [
        "A01",
        "A04",
        "A05",
        "A06",
        "A07",
        "A08",
        "A09"
      ],
      "val_subject": "A03",
      "test_subject": "A02",
      "train_sessions": [
        "T",
        "E"
      ],
      "val_sessions": [
        "T",
        "E"
      ],
      "test_sessions": [
        "T",
        "E"
      ]
    },
    "fold_2": {
      "train_subjects": [
        "A01",
        "A02",
        "A05",
        "A06",
        "A07",
        "A08",
        "A09"
      ],
      "val_subject": "A04",
      "test_subject": "A03",
      "train_sessions": [
        "T",
        "E"
      ],
      "val_sessions": [
        "T",
        "E"
      ],
      "test_sessions": [
        "T",
        "E"
      ]
    },
    "fold_3": {
      "train_subjects": [
        "A01",
        "A02",
        "A03",
        "A06",
        "A07",
        "A08",
        "A09"
      ],
      "val_subject": "A05",
      "test_subject": "A04",
      "train_sessions": [
        "T",
        "E"
      ],
      "val_sessions": [
        "T",
        "E"
      ],
      "test_sessions": [
        "T",
        "E"
      ]
    },
    "fold_4": {
      "train_subjects": [
        "A01",
        "A02",
        "A03",
        "A04",
        "A07",
        "A08",
        "A09"
      ],
      "val_subject": "A06",
      "test_subject": "A05",
      "train_sessions": [
        "T",
        "E"
      ],
      "val_sessions": [
        "T",
        "E"
      ],
      "test_sessions": [
        "T",
        "E"
      ]
    },
    "fold_5": {
      "train_subjects": [
        "A01",
        "A02",
        "A03",
        "A04",
        "A05",
        "A08",
        "A09"
      ],
      "val_subject": "A07",
      "test_subject": "A06",
      "train_sessions": [
        "T",
        "E"
      ],
      "val_sessions": [
        "T",
        "E"
      ],
      "test_sessions": [
        "T",
        "E"
      ]
    },
    "fold_6": {
      "train_subjects": [
        "A01",
        "A02",
        "A03",
        "A04",
        "A05",
        "A06",
        "A09"
      ],
      "val_subject": "A08",
      "test_subject": "A07",
      "train_sessions": [
        "T",
        "E"
      ],
      "val_sessions": [
        "T",
        "E"
      ],
      "test_sessions": [
        "T",
        "E"
      ]
    },
    "fold_7": {
      "train_subjects": [
        "A01",
        "A02",
        "A03",
        "A04",
        "A05",
        "A06",
        "A07"
      ],
      "val_subject": "A09",
      "test_subject": "A08",
      "train_sessions": [
        "T",
        "E"
      ],
      "val_sessions": [
        "T",
        "E"
      ],
      "test_sessions": [
        "T",
        "E"
      ]
    },
    "fold_8": {
      "train_subjects": [
        "A02",
        "A03",
        "A04",
        "A05",
        "A06",
        "A07",
        "A08"
      ],
      "val_subject": "A01",
      "test_subject": "A09",
      "train_sessions": [
        "T",
        "E"
      ],
      "val_sessions": [
        "T",
        "E"
      ],
      "test_sessions": [
        "T",
        "E"
      ]
    }
  }
}